s3vaultlib/__init__.py
s3vaultlib/cli.py
s3vaultlib/commands.py
s3vaultlib/s3vaultlib.py
s3vaultlib/_resources/s3vault.example.yml
s3vaultlib/_resources/ansible/s3vault_template.py
s3vaultlib/_resources/ansible/s3vault/README.md
s3vaultlib/_resources/ansible/s3vault/README.rst
s3vaultlib/_resources/ansible/s3vault/action_plugins/s3vault_template.py
s3vaultlib/_resources/ansible/s3vault/defaults/main.yml
s3vaultlib/_resources/ansible/s3vault/handlers/main.yml
s3vaultlib/_resources/ansible/s3vault/meta/main.yml
s3vaultlib/_resources/ansible/s3vault/tasks/main.yml
s3vaultlib/_resources/ansible/s3vault/tests/inventory
s3vaultlib/_resources/ansible/s3vault/tests/test.yml
s3vaultlib/_resources/ansible/s3vault/vars/main.yml
s3vaultlib/_resources/templates/bucket_policy.j2
s3vaultlib/_resources/templates/cf_template.j2
s3vaultlib/_resources/templates/groups.j2
s3vaultlib/_resources/templates/kms.j2
s3vaultlib/_resources/templates/outputs.j2
s3vaultlib/_resources/templates/roles.j2
s3vaultlib/cloudformation/__init__.py
s3vaultlib/cloudformation/policymanager.py
s3vaultlib/config/__init__.py
s3vaultlib/config/configmanager.py
s3vaultlib/config/role.py
s3vaultlib/connection/__init__.py
s3vaultlib/connection/connectionmanager.py
s3vaultlib/connection/defaults.py
s3vaultlib/connection/tokenmanager.py
s3vaultlib/editor/__init__.py
s3vaultlib/editor/autosuggestions.py
s3vaultlib/editor/completers.py
s3vaultlib/editor/editor.py
s3vaultlib/editor/utils.py
s3vaultlib/editor/validators.py
s3vaultlib/kms/__init__.py
s3vaultlib/kms/kmsresolver.py
s3vaultlib/metadata/__init__.py
s3vaultlib/metadata/base.py
s3vaultlib/metadata/ec2.py
s3vaultlib/metadata/factory.py
s3vaultlib/metadata/local.py
s3vaultlib/s3/__init__.py
s3vaultlib/s3/s3fs.py
s3vaultlib/s3/s3fsobject.py
s3vaultlib/template/__init__.py
s3vaultlib/template/templatefile.py
s3vaultlib/template/templaterenderer.py
s3vaultlib/utils/__init__.py
s3vaultlib/utils/io.py
s3vaultlib/utils/yaml.py
s3vaultlib-4.0.2.dist-info/AUTHORS.rst
s3vaultlib-4.0.2.dist-info/LICENSE
s3vaultlib-4.0.2.dist-info/METADATA
s3vaultlib-4.0.2.dist-info/WHEEL
s3vaultlib-4.0.2.dist-info/entry_points.txt
s3vaultlib-4.0.2.dist-info/top_level.txt
s3vaultlib-4.0.2.dist-info/RECORD
