Metadata-Version: 2.1
Name: s3vaultlib
Version: 4.0.2
Summary: Python library to expose S3 as vault to store encrypted data
Home-page: https://github.com/gchiesa/s3vaultlib
Author: Giuseppe Chiesa
Author-email: mail@giuseppechiesa.it
License: BSD license
Keywords: s3vaultlib
Platform: UNKNOWN
Classifier: Development Status :: 4 - Beta
Classifier: Intended Audience :: Developers
Classifier: License :: OSI Approved :: BSD License
Classifier: Natural Language :: English
Classifier: Programming Language :: Python :: 3
Classifier: Programming Language :: Python :: 3.7
Classifier: Programming Language :: Python :: 3.8
Classifier: Programming Language :: Python :: 3.9
License-File: LICENSE
License-File: AUTHORS.rst
Requires-Dist: requests (==2.26.0)
Requires-Dist: boto3 (==1.18.1)
Requires-Dist: Jinja2 (==3.0.1)
Requires-Dist: pyboto3 (==1.13.18)
Requires-Dist: python-dateutil (==2.8.2)
Requires-Dist: pytz (==2021.1)
Requires-Dist: six (==1.16.0)
Requires-Dist: python-string-utils (==1.0.0)
Requires-Dist: dpath (==2.0.1)
Requires-Dist: prompt-toolkit (==2.0.9)
Requires-Dist: Pygments (==2.9.0)
Requires-Dist: ruamel.yaml (==0.17.10)
Requires-Dist: colorlog (==5.0.1)
Requires-Dist: humanfriendly (==9.2)
